{
    "subtitles": [
        {
            "id": "PRLG_01",
            "text": "Millennia ago, gods granted magic to mankind."
        },
        {
            "id": "PRLG_02",
            "text": "A forbidden spell was born, capable of destroying entire universes."
        },
        {
            "id": "PRLG_03",
            "text": "A mage tried to wield it and failed, shattering the world into chaos."
        },
        {
            "id": "PRLG_04",
            "text": "Since then, the races sealed magic away, living in fear of its return."
        }
    ]
}